{
  "livros": [
    {
      "id": "1",
      "titulo": "A Máquina do Tempo",
      "autor": "H.G. Wells"
    },
    {
      "id": "2",
      "titulo": "A Biblioteca Invisível",
      "autor": "Genevieve Cogman"
    },
    {
      "id": "3",
      "titulo": "O Código da Vinci",
      "autor": "Dan Brown"
    },
    {
      "id": "4",
      "titulo": "Neuromancer",
      "autor": "William Gibson"
    },
    {
      "id": "5",
      "titulo": "As Crônicas Marcianas",
      "autor": "Ray Bradbury"
    },
    {
      "titulo": "Abobora",
      "autor": "sla",
      "id": "bd3e"
    }
  ]
}